patpat_viewer/__init__.py
patpat_viewer/checker.py
patpat_viewer/filter.py
patpat_viewer/finisher.py
patpat_viewer/sorter.py
patpat_viewer/utility.py
patpat_viewer/viewer.py
patpat_viewer/patpat_env/logs/tasks.json
patpat_viewer/patpat_env/result/50713921-ee56-414d-8a10-6276cb25ee22/config.json
patpat_viewer/patpat_env/result/50713921-ee56-414d-8a10-6276cb25ee22/result.json
patpat_viewer/patpat_env/result/50713921-ee56-414d-8a10-6276cb25ee22/result.tsv
patpat_viewer/patpat_env/result/725e1db0-c99e-4123-81b7-ff07daae123e/config.json
patpat_viewer/patpat_env/result/725e1db0-c99e-4123-81b7-ff07daae123e/result.json
patpat_viewer/patpat_env/result/725e1db0-c99e-4123-81b7-ff07daae123e/result.tsv
patpat_viewer/static/Patpat LOGO.png
patpat_viewer/static/logo.ico
patpat_viewer/static/putuputu.jpg
patpat_viewer/static/test.css
patpat_viewer/static/xjm.jpg
patpat_viewer/templates/404.html
patpat_viewer/templates/About.html
patpat_viewer/templates/Contact.html
patpat_viewer/templates/Dataset.html
patpat_viewer/templates/Empty.html
patpat_viewer/templates/Home.html
patpat_viewer/templates/Search.html
patpat_viewer/templates/Task.html
patpat_viewer/templates/TaskTable.html
patpat_viewer/templates/base.html
patpat_viewer/templates/macro.html
patpat_viewer/templates/test.html
patpat_viewer/templates/test2.html
patpat_viewer/templates/test3.html
patpat_viewer-0.0.7.dist-info/LICENSE
patpat_viewer-0.0.7.dist-info/METADATA
patpat_viewer-0.0.7.dist-info/WHEEL
patpat_viewer-0.0.7.dist-info/top_level.txt
patpat_viewer-0.0.7.dist-info/RECORD
