Metadata-Version: 2.1
Name: patpat-viewer
Version: 0.0.7
Summary: A viewer for Patpat
Author-email: Weiheng Liao <weiheng_liao@outlook.com>, Minyan Mo <ixxssue@outlook.com>
License: Apache 2.0
Project-URL: Homepage, https://github.com/henry-leo/Patpat-viewer
Project-URL: Bug Tracker, https://github.com/henry-leo/Patpat-viewer/issues
Classifier: Programming Language :: Python :: 3
Classifier: Operating System :: OS Independent
Requires-Python: >=3.8
License-File: LICENSE
Requires-Dist: flask
Requires-Dist: bootstrap-flask (>=2.1.0)
